CTkTableRowSelector/__init__.py
CTkTableRowSelector/__main__.py
ctktablerowselector-1.0.1.dist-info/METADATA
ctktablerowselector-1.0.1.dist-info/WHEEL
ctktablerowselector-1.0.1.dist-info/RECORD
