Metadata-Version: 2.1
Name: ctktablerowselector
Version: 1.0.1
Summary: Wrapper class around CTkTable to let users select rows
Home-page: https://github.com/CallMePixelMan/CTkTableRowSelector
License: MIT
Author: CallMePixelMan
Requires-Python: >=3.11,<4.0
Classifier: License :: OSI Approved :: MIT License
Classifier: Programming Language :: Python :: 3
Classifier: Programming Language :: Python :: 3.11
Requires-Dist: ctktable (>=0.7,<0.8)
Project-URL: Repository, https://github.com/CallMePixelMan/CTkTableRowSelector
